excel2wisxml/__init__.py
excel2wisxml/excel2wisxml.py
excel2wisxml/excel2wisxmlutils.py
excel2wisxml/templates/Metadata-guide-record.xls
excel2wisxml/templates/excel2wisxml_template.xml
excel2wisxml-3.5.7.dist-info/DESCRIPTION.rst
excel2wisxml-3.5.7.dist-info/METADATA
excel2wisxml-3.5.7.dist-info/RECORD
excel2wisxml-3.5.7.dist-info/WHEEL
excel2wisxml-3.5.7.dist-info/entry_points.txt
excel2wisxml-3.5.7.dist-info/metadata.json
excel2wisxml-3.5.7.dist-info/top_level.txt
