Metadata-Version: 2.0
Name: excel2wisxml
Version: 3.5.7
Summary: Generation of WMO Core 1.3 profile metadata
Home-page: http://openwis.github.io/openwis-documentation/projects/excel2wis/
Author: UNKNOWN
Author-email: gisc_support@meteo.fr
License: UNKNOWN
Platform: UNKNOWN
Requires-Dist: argparse
Requires-Dist: lxml
Requires-Dist: xlrd
